jumpstarter_driver_ssh/__init__.py
jumpstarter_driver_ssh/client.py
jumpstarter_driver_ssh/driver.py
jumpstarter_driver_ssh/driver_test.py
jumpstarter_driver_ssh-0.7.4.dist-info/METADATA
jumpstarter_driver_ssh-0.7.4.dist-info/WHEEL
jumpstarter_driver_ssh-0.7.4.dist-info/RECORD
