Metadata-Version: 2.4
Name: jumpstarter-driver-ssh
Version: 0.7.4
Summary: SSH wrapper driver for Jumpstarter that provides SSH CLI functionality
Project-URL: Homepage, https://jumpstarter.dev
Project-URL: source_archive, https://github.com/jumpstarter-dev/repo/archive/c5d38de69eadbb8eb0388bcfe3430a679fff0059.zip
Author-email: Miguel Angel Ajo Pelayo <miguelangel@ajo.es>
License-Expression: Apache-2.0
Requires-Python: >=3.11
Requires-Dist: anyio>=4.10.0
Requires-Dist: click>=8.0.0
Requires-Dist: jumpstarter-driver-composite==0.7.4
Requires-Dist: jumpstarter-driver-network==0.7.4
Requires-Dist: jumpstarter==0.7.4
